jiratimehook/__init__.py
jiratimehook/main.py
tool_for_time_tracking_just_proof_of_concept-0.1.1.dist-info/DESCRIPTION.rst
tool_for_time_tracking_just_proof_of_concept-0.1.1.dist-info/METADATA
tool_for_time_tracking_just_proof_of_concept-0.1.1.dist-info/RECORD
tool_for_time_tracking_just_proof_of_concept-0.1.1.dist-info/WHEEL
tool_for_time_tracking_just_proof_of_concept-0.1.1.dist-info/metadata.json
tool_for_time_tracking_just_proof_of_concept-0.1.1.dist-info/top_level.txt
