Metadata-Version: 2.0
Name: tool-for-time-tracking-just-proof-of-concept
Version: 0.1.1
Summary: UNKNOWN
Home-page: UNKNOWN
Author: UNKNOWN
Author-email: UNKNOWN
License: MIT
Platform: UNKNOWN
Requires-Dist: jira
Requires-Dist: pbr
